genwg/__init__.py
genwg/cli.py
genwg/config.py
genwg/genfiles.py
genwg/log.py
genwg/templates/bind.conf.j2
genwg/templates/bind_a_zone.j2
genwg/templates/bind_ptr_zone.j2
genwg/templates/wg_client.conf.j2
genwg/templates/wg_server.conf.j2
genwg-0.8.2.dist-info/entry_points.txt
genwg-0.8.2.dist-info/licenses/LICENSE
genwg-0.8.2.dist-info/WHEEL
genwg-0.8.2.dist-info/METADATA
genwg-0.8.2.dist-info/RECORD
