Metadata-Version: 2.4
Name: genwg
Version: 0.8.2
Summary: genwg
Author-email: gottaeat <mss@tutanota.de>
Classifier: License :: OSI Approved :: GNU General Public License v3 or later (GPLv3+)
License-File: LICENSE
Requires-Dist: PyYAML >= 6.0.0
Requires-Dist: Jinja2 >= 3.1.4
Project-URL: Source, http://github.com/gottaeat/genwg
